{
  "time": 1602743100876,
  "first10": [
    {
      "userId": 5164593345511424,
      "score": 57496344,
      "rank": 1,
      "isOwn": false,
      "name": "はとこ",
      "userCard": {
        "cardId": 111,
        "level": 60,
        "masterRank": 5,
        "specialTrainingStatus": "done",
        "defaultImage": "special_training"
      },
      "userProfile": {
        "userId": 5164593345511424,
        "word": "辛い",
        "honorId1": 57,
        "honorLevel1": 1,
        "honorId2": 105,
        "honorLevel2": 1,
        "honorId3": 81,
        "honorLevel3": 4,
        "twitterId": "",
        "profileImageType": "leader",
        "userVirtualLiveTop10Rankings": []
      }
    },
    {
      "userId": 5119914780438534,
      "score": 53250372,
      "rank": 2,
      "isOwn": false,
      "name": "ぴゅあかんぱにー",
      "userCard": {
        "cardId": 111,
        "level": 60,
        "masterRank": 5,
        "specialTrainingStatus": "done",
        "defaultImage": "special_training"
      },
      "userProfile": {
        "userId": 5119914780438534,
        "word": "ミクファン羽10/12",
        "honorId1": 82,
        "honorLevel1": 1,
        "honorId2": 126,
        "honorLevel2": 1,
        "honorId3": 118,
        "honorLevel3": 3,
        "twitterId": "kwang8ejp",
        "profileImageType": "leader",
        "userVirtualLiveTop10Rankings": []
      }
    },
    {
      "userId": 5141807818596355,
      "score": 52515090,
      "rank": 3,
      "isOwn": false,
      "name": "きゅあにな☆",
      "userCard": {
        "cardId": 111,
        "level": 60,
        "masterRank": 5,
        "specialTrainingStatus": "done",
        "defaultImage": "original"
      },
      "userProfile": {
        "userId": 5141807818596355,
        "word": "#超絶可愛いきゅあきゅあ周回　志歩同担拒否",
        "honorId1": 108,
        "honorLevel1": 1,
        "honorId2": 13,
        "honorLevel2": 4,
        "honorId3": 65,
        "honorLevel3": 1,
        "twitterId": "kure3927",
        "profileImageType": "leader",
        "userVirtualLiveTop10Rankings": []
      }
    },
    {
      "userId": 6171739449282560,
      "score": 51446254,
      "rank": 4,
      "isOwn": false,
      "name": "夏音",
      "userCard": {
        "cardId": 109,
        "level": 60,
        "masterRank": 5,
        "specialTrainingStatus": "done",
        "defaultImage": "special_training"
      },
      "userProfile": {
        "userId": 6171739449282560,
        "word": "39！",
        "honorId1": 105,
        "honorLevel1": 1,
        "honorId2": 81,
        "honorLevel2": 1,
        "honorId3": 5,
        "honorLevel3": 3,
        "twitterId": "Canon_1117",
        "profileImageType": "leader",
        "userVirtualLiveTop10Rankings": []
      }
    },
    {
      "userId": 5135204494979086,
      "score": 47742619,
      "rank": 5,
      "isOwn": false,
      "name": "しのあっとしーしー",
      "userCard": {
        "cardId": 111,
        "level": 60,
        "masterRank": 0,
        "specialTrainingStatus": "done",
        "defaultImage": "special_training"
      },
      "userProfile": {
        "userId": 5135204494979086,
        "word": "メールトー禿ーげーてしーまーいーそー♪",
        "honorId1": 108,
        "honorLevel1": 1,
        "honorId2": 1,
        "honorLevel2": 4,
        "honorId3": 5,
        "honorLevel3": 3,
        "twitterId": "4ino0",
        "profileImageType": "leader",
        "userVirtualLiveTop10Rankings": []
      }
    },
    {
      "userId": 5149627766558726,
      "score": 46044795,
      "rank": 6,
      "isOwn": false,
      "name": "きゅあぶしどー☆",
      "userCard": {
        "cardId": 109,
        "level": 60,
        "masterRank": 5,
        "specialTrainingStatus": "done",
        "defaultImage": "special_training"
      },
      "userProfile": {
        "userId": 5149627766558726,
        "word": "10/3カンストやった〜",
        "honorId1": 5,
        "honorLevel1": 5,
        "honorId2": 147,
        "honorLevel2": 1,
        "honorId3": 108,
        "honorLevel3": 1,
        "twitterId": "",
        "profileImageType": "leader",
        "userVirtualLiveTop10Rankings": []
      }
    },
    {
      "userId": 5473253955207172,
      "score": 40049820,
      "rank": 7,
      "isOwn": false,
      "name": "ぷみぃ",
      "userCard": {
        "cardId": 111,
        "level": 60,
        "masterRank": 0,
        "specialTrainingStatus": "done",
        "defaultImage": "special_training"
      },
      "userProfile": {
        "userId": 5473253955207172,
        "word": "2020/10/07start          たのしく！",
        "twitterId": "pmypjsk",
        "profileImageType": "leader",
        "userVirtualLiveTop10Rankings": []
      }
    },
    {
      "userId": 5135915236806661,
      "score": 38188723,
      "rank": 8,
      "isOwn": false,
      "name": "ワザップコロネ",
      "userCard": {
        "cardId": 111,
        "level": 60,
        "masterRank": 0,
        "specialTrainingStatus": "done",
        "defaultImage": "special_training"
      },
      "userProfile": {
        "userId": 5135915236806661,
        "word": "50位狙い",
        "honorId1": 5,
        "honorLevel1": 3,
        "honorId2": 53,
        "honorLevel2": 2,
        "honorId3": 57,
        "honorLevel3": 1,
        "twitterId": "wazapcornet",
        "profileImageType": "leader",
        "userVirtualLiveTop10Rankings": []
      }
    },
    {
      "userId": 6510064974852106,
      "score": 38052912,
      "rank": 9,
      "isOwn": false,
      "name": "世界の高橋",
      "userCard": {
        "cardId": 109,
        "level": 60,
        "masterRank": 3,
        "specialTrainingStatus": "done",
        "defaultImage": "special_training"
      },
      "userProfile": {
        "userId": 6510064974852106,
        "word": "100位狙いです",
        "honorId1": 5,
        "honorLevel1": 4,
        "honorId2": 81,
        "honorLevel2": 4,
        "honorId3": 108,
        "honorLevel3": 1,
        "twitterId": "liafinal",
        "profileImageType": "leader",
        "userVirtualLiveTop10Rankings": []
      }
    },
    {
      "userId": 5319542440161282,
      "score": 37932511,
      "rank": 10,
      "isOwn": false,
      "name": "るー",
      "userCard": {
        "cardId": 109,
        "level": 60,
        "masterRank": 5,
        "specialTrainingStatus": "done",
        "defaultImage": "special_training"
      },
      "userProfile": {
        "userId": 5319542440161282,
        "word": "頭わんだほい",
        "honorId1": 5,
        "honorLevel1": 3,
        "honorId2": 131,
        "honorLevel2": 1,
        "honorId3": 108,
        "honorLevel3": 1,
        "twitterId": "",
        "profileImageType": "leader",
        "userVirtualLiveTop10Rankings": []
      }
    }
  ],
  "rank20": [
    {
      "userId": 5655504546353164,
      "score": 26800463,
      "rank": 20,
      "isOwn": false,
      "name": "ねむい",
      "userCard": {
        "cardId": 109,
        "level": 60,
        "masterRank": 5,
        "specialTrainingStatus": "done",
        "defaultImage": "special_training"
      },
      "userProfile": {
        "userId": 5655504546353164,
        "word": "30位狙い",
        "honorId1": 127,
        "honorLevel1": 1,
        "twitterId": "",
        "profileImageType": "leader",
        "userVirtualLiveTop10Rankings": []
      }
    }
  ],
  "rank30": [
    {
      "userId": 5430292643602447,
      "score": 22227309,
      "rank": 30,
      "isOwn": false,
      "name": "のるん",
      "userCard": {
        "cardId": 109,
        "level": 60,
        "masterRank": 0,
        "specialTrainingStatus": "done",
        "defaultImage": "special_training"
      },
      "userProfile": {
        "userId": 5430292643602447,
        "word": "メルトから逃げるな",
        "honorId1": 81,
        "honorLevel1": 4,
        "honorId2": 126,
        "honorLevel2": 1,
        "honorId3": 108,
        "honorLevel3": 1,
        "twitterId": "N34890299",
        "profileImageType": "leader",
        "userVirtualLiveTop10Rankings": []
      }
    }
  ],
  "rank40": [
    {
      "userId": 5164021892616207,
      "score": 20396593,
      "rank": 40,
      "isOwn": false,
      "name": "おかめにん",
      "userCard": {
        "cardId": 111,
        "level": 60,
        "masterRank": 5,
        "specialTrainingStatus": "done",
        "defaultImage": "special_training"
      },
      "userProfile": {
        "userId": 5164021892616207,
        "word": "",
        "honorId1": 9,
        "honorLevel1": 2,
        "honorId2": 114,
        "honorLevel2": 1,
        "honorId3": 69,
        "honorLevel3": 2,
        "twitterId": "kamegbp",
        "profileImageType": "leader",
        "userVirtualLiveTop10Rankings": []
      }
    }
  ],
  "rank50": [
    {
      "userId": 5280063856156682,
      "score": 19143804,
      "rank": 50,
      "isOwn": false,
      "name": "saki",
      "userCard": {
        "cardId": 111,
        "level": 60,
        "masterRank": 5,
        "specialTrainingStatus": "done",
        "defaultImage": "special_training"
      },
      "userProfile": {
        "userId": 5280063856156682,
        "word": "えむちゃん推し　　　　　　　　　10/4ランクカンスト",
        "honorId1": 53,
        "honorLevel1": 3,
        "honorId2": 108,
        "honorLevel2": 1,
        "honorId3": 146,
        "honorLevel3": 1,
        "twitterId": "saki48837310",
        "profileImageType": "leader",
        "userVirtualLiveTop10Rankings": []
      }
    }
  ],
  "rank100": [
    {
      "userId": 5632837269082125,
      "score": 14007246,
      "rank": 100,
      "isOwn": false,
      "name": "치코",
      "userCard": {
        "cardId": 111,
        "level": 60,
        "masterRank": 0,
        "specialTrainingStatus": "done",
        "defaultImage": "special_training"
      },
      "userProfile": {
        "userId": 5632837269082125,
        "word": "赤羽駅前のクリスマス",
        "honorId1": 146,
        "honorLevel1": 1,
        "honorId2": 114,
        "honorLevel2": 1,
        "honorId3": 5,
        "honorLevel3": 3,
        "twitterId": "",
        "profileImageType": "leader",
        "userVirtualLiveTop10Rankings": []
      }
    }
  ],
  "rank200": [
    {
      "userId": 5119808723148814,
      "score": 8516133,
      "rank": 200,
      "isOwn": false,
      "name": "すずめ",
      "userCard": {
        "cardId": 111,
        "level": 60,
        "masterRank": 0,
        "specialTrainingStatus": "done",
        "defaultImage": "special_training"
      },
      "userProfile": {
        "userId": 5119808723148814,
        "word": "",
        "honorId1": 81,
        "honorLevel1": 1,
        "honorId2": 33,
        "honorLevel2": 1,
        "honorId3": 5,
        "honorLevel3": 1,
        "twitterId": "",
        "profileImageType": "leader",
        "userVirtualLiveTop10Rankings": []
      }
    }
  ],
  "rank300": [
    {
      "userId": 5299924103618568,
      "score": 6885497,
      "rank": 300,
      "isOwn": false,
      "name": "らっこ@しほさき尊い",
      "userCard": {
        "cardId": 109,
        "level": 60,
        "masterRank": 4,
        "specialTrainingStatus": "done",
        "defaultImage": "special_training"
      },
      "userProfile": {
        "userId": 5299924103618568,
        "word": "仕事しながらがんばるぅぅ",
        "honorId1": 108,
        "honorLevel1": 1,
        "honorId2": 5,
        "honorLevel2": 3,
        "honorId3": 13,
        "honorLevel3": 2,
        "twitterId": "rkpr",
        "profileImageType": "leader",
        "userVirtualLiveTop10Rankings": []
      }
    }
  ],
  "rank400": [
    {
      "userId": 5121205737328649,
      "score": 6112287,
      "rank": 400,
      "isOwn": false,
      "name": "みょん",
      "userCard": {
        "cardId": 109,
        "level": 60,
        "masterRank": 3,
        "specialTrainingStatus": "done",
        "defaultImage": "special_training"
      },
      "userProfile": {
        "userId": 5121205737328649,
        "word": "なんでピックアップしないの？？？？",
        "honorId1": 1,
        "honorLevel1": 2,
        "honorId2": 114,
        "honorLevel2": 1,
        "honorId3": 131,
        "honorLevel3": 1,
        "twitterId": "",
        "profileImageType": "leader",
        "userVirtualLiveTop10Rankings": []
      }
    }
  ],
  "rank500": [
    {
      "userId": 6001007293779976,
      "score": 5617323,
      "rank": 500,
      "isOwn": false,
      "name": "みう＠スマホ勢",
      "userCard": {
        "cardId": 109,
        "level": 60,
        "masterRank": 5,
        "specialTrainingStatus": "done",
        "defaultImage": "original"
      },
      "userProfile": {
        "userId": 6001007293779976,
        "word": "HARDまでならお任せ下さい！",
        "honorId1": 132,
        "honorLevel1": 1,
        "honorId2": 123,
        "honorLevel2": 1,
        "honorId3": 131,
        "honorLevel3": 1,
        "twitterId": "",
        "profileImageType": "leader",
        "userVirtualLiveTop10Rankings": []
      }
    }
  ],
  "rank1000": [
    {
      "userId": 5119726862864391,
      "score": 3942527,
      "rank": 1000,
      "isOwn": false,
      "name": "ぷじこぅ@",
      "userCard": {
        "cardId": 3,
        "level": 50,
        "masterRank": 5,
        "specialTrainingStatus": "done",
        "defaultImage": "special_training"
      },
      "userProfile": {
        "userId": 5119726862864391,
        "word": "くりすたるをためます",
        "honorId1": 1,
        "honorLevel1": 2,
        "honorId2": 65,
        "honorLevel2": 1,
        "honorId3": 29,
        "honorLevel3": 1,
        "twitterId": "Pujiko_streamer",
        "profileImageType": "leader",
        "userVirtualLiveTop10Rankings": []
      }
    }
  ],
  "rank2000": [
    {
      "userId": 5146059576188937,
      "score": 2387924,
      "rank": 2000,
      "isOwn": false,
      "name": "Charlotte",
      "userCard": {
        "cardId": 92,
        "level": 60,
        "masterRank": 2,
        "specialTrainingStatus": "done",
        "defaultImage": "special_training"
      },
      "userProfile": {
        "userId": 5146059576188937,
        "word": "親指勢です推しはリンちゃん、奏です",
        "honorId1": 108,
        "honorLevel1": 1,
        "honorId2": 133,
        "honorLevel2": 1,
        "honorId3": 138,
        "honorLevel3": 1,
        "twitterId": "",
        "profileImageType": "leader",
        "userVirtualLiveTop10Rankings": []
      }
    }
  ],
  "rank3000": [
    {
      "userId": 5139957874778124,
      "score": 1840498,
      "rank": 3000,
      "isOwn": false,
      "name": "ダイヤマト",
      "userCard": {
        "cardId": 110,
        "level": 60,
        "masterRank": 1,
        "specialTrainingStatus": "done",
        "defaultImage": "special_training"
      },
      "userProfile": {
        "userId": 5139957874778124,
        "word": "",
        "honorId1": 93,
        "honorLevel1": 2,
        "honorId2": 206,
        "honorLevel2": 1,
        "honorId3": 105,
        "honorLevel3": 1,
        "twitterId": "",
        "profileImageType": "leader",
        "userVirtualLiveTop10Rankings": []
      }
    }
  ],
  "rank4000": [
    {
      "userId": 5552558932299788,
      "score": 1570361,
      "rank": 4000,
      "isOwn": false,
      "name": "Hina@左手練習中",
      "userCard": {
        "cardId": 109,
        "level": 60,
        "masterRank": 2,
        "specialTrainingStatus": "done",
        "defaultImage": "special_training"
      },
      "userProfile": {
        "userId": 5552558932299788,
        "word": "エンジョイ勢",
        "honorId1": 5,
        "honorLevel1": 2,
        "honorId2": 9,
        "honorLevel2": 1,
        "honorId3": 114,
        "honorLevel3": 1,
        "twitterId": "",
        "profileImageType": "leader",
        "userVirtualLiveTop10Rankings": []
      }
    }
  ],
  "rank5000": [
    {
      "userId": 8366357846482950,
      "score": 1412001,
      "rank": 5000,
      "isOwn": false,
      "name": "honoka",
      "userCard": {
        "cardId": 50,
        "level": 30,
        "masterRank": 0,
        "specialTrainingStatus": "not_doing",
        "defaultImage": "original"
      },
      "userProfile": {
        "userId": 8366357846482950,
        "word": "",
        "honorId1": 81,
        "honorLevel1": 2,
        "honorId2": 49,
        "honorLevel2": 1,
        "honorId3": 5,
        "honorLevel3": 1,
        "twitterId": "",
        "profileImageType": "leader",
        "userVirtualLiveTop10Rankings": []
      }
    }
  ],
  "rank10000": [
    {
      "userId": 5839907201765383,
      "score": 1000929,
      "rank": 10000,
      "isOwn": false,
      "name": "Rinco",
      "userCard": {
        "cardId": 4,
        "level": 60,
        "masterRank": 2,
        "specialTrainingStatus": "done",
        "defaultImage": "special_training"
      },
      "userProfile": {
        "userId": 5839907201765383,
        "word": "",
        "honorId1": 1,
        "honorLevel1": 3,
        "honorId2": 5,
        "honorLevel2": 1,
        "honorId3": 131,
        "honorLevel3": 1,
        "twitterId": "",
        "profileImageType": "leader",
        "userVirtualLiveTop10Rankings": []
      }
    }
  ],
  "rank20000": [
    {
      "userId": 8083320852467727,
      "score": 722488,
      "rank": 20000,
      "isOwn": false,
      "name": "まめすけ",
      "userCard": {
        "cardId": 111,
        "level": 51,
        "masterRank": 0,
        "specialTrainingStatus": "done",
        "defaultImage": "special_training"
      },
      "userProfile": {
        "userId": 8083320852467727,
        "word": "",
        "twitterId": "",
        "profileImageType": "leader",
        "userVirtualLiveTop10Rankings": []
      }
    }
  ],
  "rank30000": [
    {
      "userId": 5863894380244996,
      "score": 603835,
      "rank": 30000,
      "isOwn": false,
      "name": "こゆき",
      "userCard": {
        "cardId": 109,
        "level": 60,
        "masterRank": 0,
        "specialTrainingStatus": "done",
        "defaultImage": "special_training"
      },
      "userProfile": {
        "userId": 5863894380244996,
        "word": "",
        "honorId1": 61,
        "honorLevel1": 1,
        "honorId2": 49,
        "honorLevel2": 1,
        "twitterId": "",
        "profileImageType": "leader",
        "userVirtualLiveTop10Rankings": []
      }
    }
  ],
  "rank40000": [
    {
      "userId": 6645247341780997,
      "score": 527358,
      "rank": 40000,
      "isOwn": false,
      "name": "メリ",
      "userCard": {
        "cardId": 3,
        "level": 40,
        "masterRank": 0,
        "specialTrainingStatus": "not_doing",
        "defaultImage": "original"
      },
      "userProfile": {
        "userId": 6645247341780997,
        "word": "",
        "honorId1": 145,
        "honorLevel1": 1,
        "honorId2": 69,
        "honorLevel2": 1,
        "honorId3": 65,
        "honorLevel3": 1,
        "twitterId": "",
        "profileImageType": "leader",
        "userVirtualLiveTop10Rankings": []
      }
    }
  ],
  "rank50000": [
    {
      "userId": 5580690658320387,
      "score": 472417,
      "rank": 50000,
      "isOwn": false,
      "name": "ショウ",
      "userCard": {
        "cardId": 3,
        "level": 38,
        "masterRank": 0,
        "specialTrainingStatus": "not_doing",
        "defaultImage": "original"
      },
      "userProfile": {
        "userId": 5580690658320387,
        "word": "。",
        "honorId1": 1,
        "honorLevel1": 2,
        "honorId2": 136,
        "honorLevel2": 1,
        "honorId3": 138,
        "honorLevel3": 1,
        "twitterId": "",
        "profileImageType": "leader",
        "userVirtualLiveTop10Rankings": []
      }
    }
  ],
  "rank100000": [
    {
      "userId": 5119715484319755,
      "score": 319312,
      "rank": 100000,
      "isOwn": false,
      "name": "うい",
      "userCard": {
        "cardId": 99,
        "level": 50,
        "masterRank": 0,
        "specialTrainingStatus": "done",
        "defaultImage": "special_training"
      },
      "userProfile": {
        "userId": 5119715484319755,
        "word": "",
        "honorId1": 81,
        "honorLevel1": 1,
        "honorId2": 105,
        "honorLevel2": 1,
        "honorId3": 133,
        "honorLevel3": 1,
        "twitterId": "",
        "profileImageType": "leader",
        "userVirtualLiveTop10Rankings": []
      }
    }
  ]
}