{
  "time": 1603185718757,
  "first10": [
    {
      "userId": 5836388876832774,
      "score": 1868480,
      "rank": 1,
      "isOwn": false,
      "name": "てつ",
      "userCard": {
        "cardId": 116,
        "level": 60,
        "masterRank": 5,
        "specialTrainingStatus": "done",
        "defaultImage": "special_training"
      },
      "userProfile": {
        "userId": 5836388876832774,
        "word": "",
        "honorId1": 189,
        "honorLevel1": 1,
        "honorId2": 9,
        "honorLevel2": 2,
        "honorId3": 5,
        "honorLevel3": 4,
        "twitterId": "ttgrp11",
        "profileImageType": "leader",
        "userVirtualLiveTop10Rankings": []
      }
    },
    {
      "userId": 5253523474546692,
      "score": 1775106,
      "rank": 2,
      "isOwn": false,
      "name": "りや",
      "userCard": {
        "cardId": 114,
        "level": 60,
        "masterRank": 3,
        "specialTrainingStatus": "done",
        "defaultImage": "original"
      },
      "userProfile": {
        "userId": 5253523474546692,
        "word": "まふゆちゃんかわいい",
        "honorId1": 69,
        "honorLevel1": 3,
        "honorId2": 133,
        "honorLevel2": 1,
        "honorId3": 108,
        "honorLevel3": 1,
        "twitterId": "rsla_ry",
        "profileImageType": "leader",
        "userVirtualLiveTop10Rankings": []
      }
    },
    {
      "userId": 5945854700036104,
      "score": 1506203,
      "rank": 3,
      "isOwn": false,
      "name": "obaco",
      "userCard": {
        "cardId": 75,
        "level": 50,
        "masterRank": 5,
        "specialTrainingStatus": "done",
        "defaultImage": "special_training"
      },
      "userProfile": {
        "userId": 5945854700036104,
        "word": "趣味:服作り",
        "honorId1": 73,
        "honorLevel1": 4,
        "twitterId": "ObacoPoke",
        "profileImageType": "leader",
        "userVirtualLiveTop10Rankings": []
      }
    },
    {
      "userId": 5817274494091278,
      "score": 1469248,
      "rank": 4,
      "isOwn": false,
      "name": "shupein",
      "userCard": {
        "cardId": 114,
        "level": 60,
        "masterRank": 0,
        "specialTrainingStatus": "done",
        "defaultImage": "special_training"
      },
      "userProfile": {
        "userId": 5817274494091278,
        "word": "25時、リベンジします…？　　　25252525p目標",
        "honorId1": 191,
        "honorLevel1": 1,
        "honorId2": 108,
        "honorLevel2": 1,
        "honorId3": 146,
        "honorLevel3": 1,
        "twitterId": "",
        "profileImageType": "leader",
        "userVirtualLiveTop10Rankings": []
      }
    },
    {
      "userId": 5191395686408198,
      "score": 1467264,
      "rank": 5,
      "isOwn": false,
      "name": "nia",
      "userCard": {
        "cardId": 115,
        "level": 60,
        "masterRank": 5,
        "specialTrainingStatus": "done",
        "defaultImage": "special_training"
      },
      "userProfile": {
        "userId": 5191395686408198,
        "word": "ニーゴ推してきます",
        "honorId1": 65,
        "honorLevel1": 4,
        "honorId2": 77,
        "honorLevel2": 2,
        "honorId3": 197,
        "honorLevel3": 1,
        "twitterId": "niasephiroth",
        "profileImageType": "leader",
        "userVirtualLiveTop10Rankings": []
      }
    },
    {
      "userId": 5150812749938696,
      "score": 1315217,
      "rank": 6,
      "isOwn": false,
      "name": "きゅあゆり☆",
      "userCard": {
        "cardId": 115,
        "level": 60,
        "masterRank": 1,
        "specialTrainingStatus": "done",
        "defaultImage": "special_training"
      },
      "userProfile": {
        "userId": 5150812749938696,
        "word": "絵名しか勝たん",
        "honorId1": 73,
        "honorLevel1": 2,
        "twitterId": "enashikakatan",
        "profileImageType": "leader",
        "userVirtualLiveTop10Rankings": []
      }
    },
    {
      "userId": 5456229015302156,
      "score": 1212975,
      "rank": 7,
      "isOwn": false,
      "name": "そまり",
      "userCard": {
        "cardId": 114,
        "level": 60,
        "masterRank": 0,
        "specialTrainingStatus": "done",
        "defaultImage": "special_training"
      },
      "userProfile": {
        "userId": 5456229015302156,
        "word": "10/12カンスト",
        "honorId1": 195,
        "honorLevel1": 1,
        "honorId2": 73,
        "honorLevel2": 3,
        "honorId3": 81,
        "honorLevel3": 2,
        "twitterId": "somariREOLLL",
        "profileImageType": "leader",
        "userVirtualLiveTop10Rankings": []
      }
    },
    {
      "userId": 5555767843225614,
      "score": 1138487,
      "rank": 8,
      "isOwn": false,
      "name": "セカイの住人",
      "userCard": {
        "cardId": 116,
        "level": 60,
        "masterRank": 0,
        "specialTrainingStatus": "done",
        "defaultImage": "special_training"
      },
      "userProfile": {
        "userId": 5555767843225614,
        "word": "ニーゴミクとかいう天使",
        "honorId1": 81,
        "honorLevel1": 2,
        "honorId2": 226,
        "honorLevel2": 1,
        "honorId3": 105,
        "honorLevel3": 1,
        "twitterId": "",
        "profileImageType": "leader",
        "userVirtualLiveTop10Rankings": []
      }
    },
    {
      "userId": 5135586663047175,
      "score": 1112450,
      "rank": 9,
      "isOwn": false,
      "name": "†東雲える†",
      "userCard": {
        "cardId": 115,
        "level": 60,
        "masterRank": 5,
        "specialTrainingStatus": "done",
        "defaultImage": "special_training"
      },
      "userProfile": {
        "userId": 5135586663047175,
        "word": "にゃー　",
        "honorId1": 196,
        "honorLevel1": 1,
        "honorId2": 73,
        "honorLevel2": 2,
        "honorId3": 77,
        "honorLevel3": 2,
        "twitterId": "",
        "profileImageType": "leader",
        "userVirtualLiveTop10Rankings": []
      }
    },
    {
      "userId": 5300483690344459,
      "score": 988078,
      "rank": 10,
      "isOwn": false,
      "name": "とびうお",
      "userCard": {
        "cardId": 75,
        "level": 50,
        "masterRank": 5,
        "specialTrainingStatus": "done",
        "defaultImage": "original"
      },
      "userProfile": {
        "userId": 5300483690344459,
        "word": "みずえな推し IDにアンダーバーつかない",
        "honorId1": 73,
        "honorLevel1": 3,
        "honorId2": 77,
        "honorLevel2": 2,
        "honorId3": 222,
        "honorLevel3": 1,
        "twitterId": "Mzenouo",
        "profileImageType": "leader",
        "userVirtualLiveTop10Rankings": []
      }
    }
  ],
  "rank20": [
    {
      "userId": 6702388660862986,
      "score": 845708,
      "rank": 20,
      "isOwn": false,
      "name": "잘자콘",
      "userCard": {
        "cardId": 116,
        "level": 60,
        "masterRank": 5,
        "specialTrainingStatus": "done",
        "defaultImage": "special_training"
      },
      "userProfile": {
        "userId": 6702388660862986,
        "word": "お休みー",
        "honorId1": 190,
        "honorLevel1": 1,
        "honorId2": 146,
        "honorLevel2": 1,
        "honorId3": 108,
        "honorLevel3": 1,
        "twitterId": "F_Seivelun",
        "profileImageType": "leader",
        "userVirtualLiveTop10Rankings": []
      }
    }
  ],
  "rank30": [
    {
      "userId": 5138198602792968,
      "score": 790052,
      "rank": 30,
      "isOwn": false,
      "name": "Ne-tsu",
      "userCard": {
        "cardId": 114,
        "level": 60,
        "masterRank": 2,
        "specialTrainingStatus": "done",
        "defaultImage": "special_training"
      },
      "userProfile": {
        "userId": 5138198602792968,
        "word": "寧々ちゃん最推し。司君推し。の箱推し。",
        "honorId1": 57,
        "honorLevel1": 4,
        "honorId2": 218,
        "honorLevel2": 1,
        "honorId3": 202,
        "honorLevel3": 1,
        "twitterId": "",
        "profileImageType": "leader",
        "userVirtualLiveTop10Rankings": []
      }
    }
  ],
  "rank40": [
    {
      "userId": 5144185590161408,
      "score": 702105,
      "rank": 40,
      "isOwn": false,
      "name": "たき",
      "userCard": {
        "cardId": 115,
        "level": 60,
        "masterRank": 3,
        "specialTrainingStatus": "done",
        "defaultImage": "special_training"
      },
      "userProfile": {
        "userId": 5144185590161408,
        "word": "",
        "honorId1": 65,
        "honorLevel1": 2,
        "honorId2": 81,
        "honorLevel2": 1,
        "honorId3": 85,
        "honorLevel3": 1,
        "twitterId": "",
        "profileImageType": "leader",
        "userVirtualLiveTop10Rankings": []
      }
    }
  ],
  "rank50": [
    {
      "userId": 5251035119747076,
      "score": 651623,
      "rank": 50,
      "isOwn": false,
      "name": "DAL",
      "userCard": {
        "cardId": 116,
        "level": 60,
        "masterRank": 2,
        "specialTrainingStatus": "done",
        "defaultImage": "special_training"
      },
      "userProfile": {
        "userId": 5251035119747076,
        "word": "ニーゴイベがんばろー",
        "honorId1": 73,
        "honorLevel1": 2,
        "honorId2": 105,
        "honorLevel2": 1,
        "honorId3": 107,
        "honorLevel3": 1,
        "twitterId": "",
        "profileImageType": "leader",
        "userVirtualLiveTop10Rankings": []
      }
    }
  ],
  "rank100": [
    {
      "userId": 5824983083724810,
      "score": 521943,
      "rank": 100,
      "isOwn": false,
      "name": "ジブお",
      "userCard": {
        "cardId": 69,
        "level": 20,
        "masterRank": 0,
        "specialTrainingStatus": "not_doing",
        "defaultImage": "original"
      },
      "userProfile": {
        "userId": 5824983083724810,
        "word": "よろしくお願いします。",
        "honorId1": 201,
        "honorLevel1": 1,
        "honorId2": 133,
        "honorLevel2": 1,
        "honorId3": 130,
        "honorLevel3": 1,
        "twitterId": "",
        "profileImageType": "leader",
        "userVirtualLiveTop10Rankings": []
      }
    }
  ],
  "rank200": [
    {
      "userId": 5151425491664904,
      "score": 409407,
      "rank": 200,
      "isOwn": false,
      "name": "り",
      "userCard": {
        "cardId": 114,
        "level": 60,
        "masterRank": 0,
        "specialTrainingStatus": "done",
        "defaultImage": "special_training"
      },
      "userProfile": {
        "userId": 5151425491664904,
        "word": "",
        "honorId1": 65,
        "honorLevel1": 2,
        "honorId2": 69,
        "honorLevel2": 1,
        "honorId3": 77,
        "honorLevel3": 1,
        "twitterId": "",
        "profileImageType": "leader",
        "userVirtualLiveTop10Rankings": []
      }
    }
  ],
  "rank300": [
    {
      "userId": 5119580436164608,
      "score": 362457,
      "rank": 300,
      "isOwn": false,
      "name": "2032",
      "userCard": {
        "cardId": 75,
        "level": 50,
        "masterRank": 5,
        "specialTrainingStatus": "done",
        "defaultImage": "original"
      },
      "userProfile": {
        "userId": 5119580436164608,
        "word": "",
        "honorId1": 73,
        "honorLevel1": 3,
        "honorId2": 108,
        "honorLevel2": 1,
        "honorId3": 77,
        "honorLevel3": 1,
        "twitterId": "",
        "profileImageType": "leader",
        "userVirtualLiveTop10Rankings": []
      }
    }
  ],
  "rank400": [
    {
      "userId": 5205176160133131,
      "score": 325030,
      "rank": 400,
      "isOwn": false,
      "name": "みみぼう",
      "userCard": {
        "cardId": 75,
        "level": 50,
        "masterRank": 0,
        "specialTrainingStatus": "done",
        "defaultImage": "special_training"
      },
      "userProfile": {
        "userId": 5205176160133131,
        "word": "リリース待ってた〜〜〜〜！！！",
        "honorId1": 131,
        "honorLevel1": 1,
        "honorId2": 81,
        "honorLevel2": 2,
        "honorId3": 105,
        "honorLevel3": 1,
        "twitterId": "mimi79673342",
        "profileImageType": "leader",
        "userVirtualLiveTop10Rankings": []
      }
    }
  ],
  "rank500": [
    {
      "userId": 6219895901786121,
      "score": 294418,
      "rank": 500,
      "isOwn": false,
      "name": "知世",
      "userCard": {
        "cardId": 96,
        "level": 60,
        "masterRank": 0,
        "specialTrainingStatus": "done",
        "defaultImage": "special_training"
      },
      "userProfile": {
        "userId": 6219895901786121,
        "word": "",
        "honorId1": 69,
        "honorLevel1": 2,
        "honorId2": 65,
        "honorLevel2": 1,
        "honorId3": 77,
        "honorLevel3": 1,
        "twitterId": "yuubinn701",
        "profileImageType": "leader",
        "userVirtualLiveTop10Rankings": []
      }
    }
  ],
  "rank1000": [
    {
      "userId": 5203630571913231,
      "score": 220068,
      "rank": 1000,
      "isOwn": false,
      "name": "ももちこ",
      "userCard": {
        "cardId": 75,
        "level": 50,
        "masterRank": 0,
        "specialTrainingStatus": "done",
        "defaultImage": "special_training"
      },
      "userProfile": {
        "userId": 5203630571913231,
        "word": "",
        "honorId1": 81,
        "honorLevel1": 1,
        "honorId2": 105,
        "honorLevel2": 1,
        "honorId3": 130,
        "honorLevel3": 1,
        "twitterId": "",
        "profileImageType": "leader",
        "userVirtualLiveTop10Rankings": []
      }
    }
  ],
  "rank2000": [
    {
      "userId": 5120104950673410,
      "score": 160643,
      "rank": 2000,
      "isOwn": false,
      "name": "お",
      "userCard": {
        "cardId": 78,
        "level": 25,
        "masterRank": 0,
        "specialTrainingStatus": "not_doing",
        "defaultImage": "original"
      },
      "userProfile": {
        "userId": 5120104950673410,
        "word": "",
        "honorId1": 200,
        "honorLevel1": 1,
        "honorId2": 5,
        "honorLevel2": 1,
        "honorId3": 13,
        "honorLevel3": 1,
        "twitterId": "",
        "profileImageType": "leader",
        "userVirtualLiveTop10Rankings": []
      }
    }
  ],
  "rank3000": [
    {
      "userId": 5172806808035334,
      "score": 133060,
      "rank": 3000,
      "isOwn": false,
      "name": "リヒト@青廃",
      "userCard": {
        "cardId": 116,
        "level": 60,
        "masterRank": 0,
        "specialTrainingStatus": "done",
        "defaultImage": "special_training"
      },
      "userProfile": {
        "userId": 5172806808035334,
        "word": "下手ですがよろしくお願いします",
        "honorId1": 101,
        "honorLevel1": 2,
        "honorId2": 145,
        "honorLevel2": 1,
        "honorId3": 198,
        "honorLevel3": 1,
        "twitterId": "Gakuranparkerw",
        "profileImageType": "leader",
        "userVirtualLiveTop10Rankings": []
      }
    }
  ],
  "rank4000": [
    {
      "userId": 5176665907597324,
      "score": 112974,
      "rank": 4000,
      "isOwn": false,
      "name": "そら",
      "userCard": {
        "cardId": 75,
        "level": 47,
        "masterRank": 0,
        "specialTrainingStatus": "done",
        "defaultImage": "special_training"
      },
      "userProfile": {
        "userId": 5176665907597324,
        "word": "",
        "honorId1": 114,
        "honorLevel1": 1,
        "honorId2": 25,
        "honorLevel2": 2,
        "honorId3": 1,
        "honorLevel3": 1,
        "twitterId": "",
        "profileImageType": "leader",
        "userVirtualLiveTop10Rankings": []
      }
    }
  ],
  "rank5000": [
    {
      "userId": 5272514406141966,
      "score": 99287,
      "rank": 5000,
      "isOwn": false,
      "name": "Sena",
      "userCard": {
        "cardId": 88,
        "level": 60,
        "masterRank": 0,
        "specialTrainingStatus": "done",
        "defaultImage": "special_training"
      },
      "userProfile": {
        "userId": 5272514406141966,
        "word": "冬弥を愛してます",
        "honorId1": 45,
        "honorLevel1": 1,
        "honorId2": 85,
        "honorLevel2": 1,
        "honorId3": 89,
        "honorLevel3": 1,
        "twitterId": "",
        "profileImageType": "leader",
        "userVirtualLiveTop10Rankings": []
      }
    }
  ],
  "rank10000": [
    {
      "userId": 5200778084532239,
      "score": 65440,
      "rank": 10000,
      "isOwn": false,
      "name": "アキ",
      "userCard": {
        "cardId": 87,
        "level": 50,
        "masterRank": 1,
        "specialTrainingStatus": "done",
        "defaultImage": "special_training"
      },
      "userProfile": {
        "userId": 5200778084532239,
        "word": "",
        "honorId1": 45,
        "honorLevel1": 1,
        "twitterId": "",
        "profileImageType": "leader",
        "userVirtualLiveTop10Rankings": []
      }
    }
  ],
  "rank20000": [
    {
      "userId": 5119763596800006,
      "score": 45332,
      "rank": 20000,
      "isOwn": false,
      "name": "おもち",
      "userCard": {
        "cardId": 115,
        "level": 12,
        "masterRank": 0,
        "specialTrainingStatus": "not_doing",
        "defaultImage": "original"
      },
      "userProfile": {
        "userId": 5119763596800006,
        "word": "下手っぴだけど仲良くしてください！よろしく⸜(*´꒳​`*)",
        "honorId1": 65,
        "honorLevel1": 1,
        "honorId2": 133,
        "honorLevel2": 1,
        "honorId3": 127,
        "honorLevel3": 1,
        "twitterId": "omochiKSG",
        "profileImageType": "leader",
        "userVirtualLiveTop10Rankings": []
      }
    }
  ],
  "rank30000": [
    {
      "userId": 8301622300749836,
      "score": 37572,
      "rank": 30000,
      "isOwn": false,
      "name": "ふまき",
      "userCard": {
        "cardId": 51,
        "level": 50,
        "masterRank": 1,
        "specialTrainingStatus": "done",
        "defaultImage": "special_training"
      },
      "userProfile": {
        "userId": 8301622300749836,
        "word": "今日も元気にわんだほーい☆",
        "honorId1": 53,
        "honorLevel1": 1,
        "honorId2": 61,
        "honorLevel2": 1,
        "honorId3": 57,
        "honorLevel3": 1,
        "twitterId": "",
        "profileImageType": "leader",
        "userVirtualLiveTop10Rankings": []
      }
    }
  ],
  "rank40000": [
    {
      "userId": 7418718225829889,
      "score": 32872,
      "rank": 40000,
      "isOwn": false,
      "name": "えらさ。",
      "userCard": {
        "cardId": 96,
        "level": 49,
        "masterRank": 1,
        "specialTrainingStatus": "not_doing",
        "defaultImage": "original"
      },
      "userProfile": {
        "userId": 7418718225829889,
        "profileImageType": "leader",
        "userVirtualLiveTop10Rankings": []
      }
    }
  ],
  "rank50000": [
    {
      "userId": 5901781910163466,
      "score": 29361,
      "rank": 50000,
      "isOwn": false,
      "name": "あいがも",
      "userCard": {
        "cardId": 109,
        "level": 60,
        "masterRank": 0,
        "specialTrainingStatus": "done",
        "defaultImage": "special_training"
      },
      "userProfile": {
        "userId": 5901781910163466,
        "word": "",
        "honorId1": 5,
        "honorLevel1": 2,
        "honorId2": 25,
        "honorLevel2": 1,
        "honorId3": 33,
        "honorLevel3": 1,
        "twitterId": "",
        "profileImageType": "leader",
        "userVirtualLiveTop10Rankings": []
      }
    }
  ],
  "rank100000": [
    {
      "userId": 5232969203740683,
      "score": 17871,
      "rank": 100000,
      "isOwn": false,
      "name": "カズキ",
      "userCard": {
        "cardId": 88,
        "level": 60,
        "masterRank": 0,
        "specialTrainingStatus": "done",
        "defaultImage": "special_training"
      },
      "userProfile": {
        "userId": 5232969203740683,
        "word": "",
        "twitterId": "",
        "profileImageType": "leader",
        "userVirtualLiveTop10Rankings": []
      }
    }
  ]
}