{
  "time": 1602399000907,
  "first10": [
    {
      "userId": 5149627766558726,
      "score": 22277962,
      "rank": 1,
      "isOwn": false,
      "name": "きゅあぶしどー☆",
      "userCard": {
        "cardId": 109,
        "level": 60,
        "masterRank": 5,
        "specialTrainingStatus": "done",
        "defaultImage": "special_training"
      },
      "userProfile": {
        "userId": 5149627766558726,
        "word": "10/3カンストやった〜",
        "honorId1": 108,
        "honorLevel1": 1,
        "honorId2": 113,
        "honorLevel2": 1,
        "honorId3": 5,
        "honorLevel3": 3,
        "twitterId": "",
        "profileImageType": "leader",
        "userVirtualLiveTop10Rankings": []
      }
    },
    {
      "userId": 5164593345511424,
      "score": 21979973,
      "rank": 2,
      "isOwn": false,
      "name": "はとこ",
      "userCard": {
        "cardId": 111,
        "level": 60,
        "masterRank": 5,
        "specialTrainingStatus": "done",
        "defaultImage": "special_training"
      },
      "userProfile": {
        "userId": 5164593345511424,
        "word": "辛い",
        "honorId1": 57,
        "honorLevel1": 1,
        "honorId2": 105,
        "honorLevel2": 1,
        "honorId3": 81,
        "honorLevel3": 4,
        "twitterId": "",
        "profileImageType": "leader",
        "userVirtualLiveTop10Rankings": []
      }
    },
    {
      "userId": 5141807818596355,
      "score": 21153043,
      "rank": 3,
      "isOwn": false,
      "name": "きゅあにな☆",
      "userCard": {
        "cardId": 109,
        "level": 60,
        "masterRank": 2,
        "specialTrainingStatus": "done",
        "defaultImage": "special_training"
      },
      "userProfile": {
        "userId": 5141807818596355,
        "word": "10/2最速ランクカンスト！",
        "honorId1": 108,
        "honorLevel1": 1,
        "honorId2": 13,
        "honorLevel2": 2,
        "honorId3": 65,
        "honorLevel3": 1,
        "twitterId": "kure3927",
        "profileImageType": "leader",
        "userVirtualLiveTop10Rankings": []
      }
    },
    {
      "userId": 5119914780438534,
      "score": 20596880,
      "rank": 4,
      "isOwn": false,
      "name": "かんぱり",
      "userCard": {
        "cardId": 111,
        "level": 60,
        "masterRank": 5,
        "specialTrainingStatus": "done",
        "defaultImage": "special_training"
      },
      "userProfile": {
        "userId": 5119914780438534,
        "word": "カンスト10/9",
        "honorId1": 126,
        "honorLevel1": 1,
        "honorId2": 81,
        "honorLevel2": 5,
        "honorId3": 118,
        "honorLevel3": 3,
        "twitterId": "",
        "profileImageType": "leader",
        "userVirtualLiveTop10Rankings": []
      }
    },
    {
      "userId": 5135204494979086,
      "score": 17631780,
      "rank": 5,
      "isOwn": false,
      "name": "しの",
      "userCard": {
        "cardId": 111,
        "level": 60,
        "masterRank": 0,
        "specialTrainingStatus": "done",
        "defaultImage": "special_training"
      },
      "userProfile": {
        "userId": 5135204494979086,
        "word": "10/8ランカン！メルトメルト",
        "honorId1": 1,
        "honorLevel1": 3,
        "honorId2": 108,
        "honorLevel2": 1,
        "honorId3": 111,
        "honorLevel3": 1,
        "twitterId": "4ino0",
        "profileImageType": "leader",
        "userVirtualLiveTop10Rankings": []
      }
    },
    {
      "userId": 5473253955207172,
      "score": 14158117,
      "rank": 6,
      "isOwn": false,
      "name": "ぷみぃ",
      "userCard": {
        "cardId": 111,
        "level": 60,
        "masterRank": 0,
        "specialTrainingStatus": "done",
        "defaultImage": "special_training"
      },
      "userProfile": {
        "userId": 5473253955207172,
        "word": "2020/10/07start イベ一緒に回る人がおらん",
        "twitterId": "pmypjsk",
        "profileImageType": "leader",
        "userVirtualLiveTop10Rankings": []
      }
    },
    {
      "userId": 6171739449282560,
      "score": 14145273,
      "rank": 7,
      "isOwn": false,
      "name": "夏音",
      "userCard": {
        "cardId": 109,
        "level": 60,
        "masterRank": 5,
        "specialTrainingStatus": "done",
        "defaultImage": "special_training"
      },
      "userProfile": {
        "userId": 6171739449282560,
        "word": "39！",
        "honorId1": 105,
        "honorLevel1": 1,
        "honorId2": 81,
        "honorLevel2": 1,
        "honorId3": 5,
        "honorLevel3": 2,
        "twitterId": "Canon_1117",
        "profileImageType": "leader",
        "userVirtualLiveTop10Rankings": []
      }
    },
    {
      "userId": 5185216327225356,
      "score": 13424480,
      "rank": 8,
      "isOwn": false,
      "name": "きゅあひーねこ☆",
      "userCard": {
        "cardId": 109,
        "level": 60,
        "masterRank": 0,
        "specialTrainingStatus": "done",
        "defaultImage": "special_training"
      },
      "userProfile": {
        "userId": 5185216327225356,
        "word": "ぬかしまー",
        "honorId1": 108,
        "honorLevel1": 1,
        "honorId2": 89,
        "honorLevel2": 2,
        "honorId3": 85,
        "honorLevel3": 3,
        "twitterId": "hinekras",
        "profileImageType": "leader",
        "userVirtualLiveTop10Rankings": []
      }
    },
    {
      "userId": 5135915236806661,
      "score": 13051674,
      "rank": 9,
      "isOwn": false,
      "name": "Hello",
      "userCard": {
        "cardId": 109,
        "level": 60,
        "masterRank": 5,
        "specialTrainingStatus": "done",
        "defaultImage": "special_training"
      },
      "userProfile": {
        "userId": 5135915236806661,
        "word": "50位狙い",
        "twitterId": "wazapcornet",
        "profileImageType": "leader",
        "userVirtualLiveTop10Rankings": []
      }
    },
    {
      "userId": 5170669297913864,
      "score": 12793343,
      "rank": 10,
      "isOwn": false,
      "name": "5chから来ました",
      "userCard": {
        "cardId": 109,
        "level": 60,
        "masterRank": 0,
        "specialTrainingStatus": "done",
        "defaultImage": "special_training"
      },
      "userProfile": {
        "userId": 5170669297913864,
        "word": "スレ民",
        "honorId1": 130,
        "honorLevel1": 1,
        "honorId2": 123,
        "honorLevel2": 1,
        "honorId3": 235,
        "honorLevel3": 1,
        "twitterId": "",
        "profileImageType": "leader",
        "userVirtualLiveTop10Rankings": []
      }
    }
  ],
  "rank20": [
    {
      "userId": 5204678694535177,
      "score": 9813758,
      "rank": 20,
      "isOwn": false,
      "name": "ピーチ姫",
      "userCard": {
        "cardId": 111,
        "level": 60,
        "masterRank": 0,
        "specialTrainingStatus": "done",
        "defaultImage": "special_training"
      },
      "userProfile": {
        "userId": 5204678694535177,
        "word": "このイベント走る必要ありますか？",
        "honorId1": 108,
        "honorLevel1": 1,
        "honorId2": 81,
        "honorLevel2": 3,
        "honorId3": 113,
        "honorLevel3": 1,
        "twitterId": "Peachhime1022",
        "profileImageType": "leader",
        "userVirtualLiveTop10Rankings": []
      }
    }
  ],
  "rank30": [
    {
      "userId": 5729647111352323,
      "score": 8723810,
      "rank": 30,
      "isOwn": false,
      "name": "ゆぅ",
      "userCard": {
        "cardId": 111,
        "level": 60,
        "masterRank": 3,
        "specialTrainingStatus": "done",
        "defaultImage": "special_training"
      },
      "userProfile": {
        "userId": 5729647111352323,
        "word": "",
        "honorId1": 13,
        "honorLevel1": 2,
        "honorId2": 1,
        "honorLevel2": 2,
        "honorId3": 145,
        "honorLevel3": 1,
        "twitterId": "yuashs",
        "profileImageType": "leader",
        "userVirtualLiveTop10Rankings": []
      }
    }
  ],
  "rank40": [
    {
      "userId": 5283394632429568,
      "score": 7579422,
      "rank": 40,
      "isOwn": false,
      "name": "エルメルリア",
      "userCard": {
        "cardId": 109,
        "level": 60,
        "masterRank": 5,
        "specialTrainingStatus": "done",
        "defaultImage": "special_training"
      },
      "userProfile": {
        "userId": 5283394632429568,
        "word": "",
        "honorId1": 5,
        "honorLevel1": 3,
        "honorId2": 1,
        "honorLevel2": 2,
        "honorId3": 81,
        "honorLevel3": 1,
        "twitterId": "silverchariot96",
        "profileImageType": "leader",
        "userVirtualLiveTop10Rankings": []
      }
    }
  ],
  "rank50": [
    {
      "userId": 5251077226897414,
      "score": 7120307,
      "rank": 50,
      "isOwn": false,
      "name": "アルストロメリア　W",
      "userCard": {
        "cardId": 88,
        "level": 60,
        "masterRank": 2,
        "specialTrainingStatus": "done",
        "defaultImage": "special_training"
      },
      "userProfile": {
        "userId": 5251077226897414,
        "word": "",
        "honorId1": 129,
        "honorLevel1": 1,
        "honorId2": 105,
        "honorLevel2": 1,
        "honorId3": 81,
        "honorLevel3": 2,
        "twitterId": "",
        "profileImageType": "leader",
        "userVirtualLiveTop10Rankings": []
      }
    }
  ],
  "rank100": [
    {
      "userId": 5200349527359498,
      "score": 5130369,
      "rank": 100,
      "isOwn": false,
      "name": "くろ",
      "userCard": {
        "cardId": 88,
        "level": 60,
        "masterRank": 3,
        "specialTrainingStatus": "done",
        "defaultImage": "special_training"
      },
      "userProfile": {
        "userId": 5200349527359498,
        "word": "不慣れではありますがよろしくお願いします",
        "honorId1": 108,
        "honorLevel1": 1,
        "honorId2": 85,
        "honorLevel2": 1,
        "honorId3": 81,
        "honorLevel3": 2,
        "twitterId": "",
        "profileImageType": "leader",
        "userVirtualLiveTop10Rankings": []
      }
    }
  ],
  "rank200": [
    {
      "userId": 6946471283113995,
      "score": 3512308,
      "rank": 200,
      "isOwn": false,
      "name": "DMAN",
      "userCard": {
        "cardId": 109,
        "level": 60,
        "masterRank": 0,
        "specialTrainingStatus": "done",
        "defaultImage": "special_training"
      },
      "userProfile": {
        "userId": 6946471283113995,
        "word": "2020/10/5から",
        "honorId1": 81,
        "honorLevel1": 1,
        "honorId2": 41,
        "honorLevel2": 1,
        "honorId3": 123,
        "honorLevel3": 1,
        "twitterId": "",
        "profileImageType": "leader",
        "userVirtualLiveTop10Rankings": []
      }
    }
  ],
  "rank300": [
    {
      "userId": 5189619063406600,
      "score": 2863296,
      "rank": 300,
      "isOwn": false,
      "name": "ﾈｺｵｵ効率曲ごめん",
      "userCard": {
        "cardId": 51,
        "level": 50,
        "masterRank": 0,
        "specialTrainingStatus": "done",
        "defaultImage": "special_training"
      },
      "userProfile": {
        "userId": 5189619063406600,
        "word": "リリース初日〜play",
        "honorId1": 111,
        "honorLevel1": 1,
        "honorId2": 107,
        "honorLevel2": 1,
        "honorId3": 131,
        "honorLevel3": 1,
        "twitterId": "kerakeraa09",
        "profileImageType": "leader",
        "userVirtualLiveTop10Rankings": []
      }
    }
  ],
  "rank400": [
    {
      "userId": 5336465651625988,
      "score": 2559903,
      "rank": 400,
      "isOwn": false,
      "name": "切断すんなクズども",
      "userCard": {
        "cardId": 88,
        "level": 60,
        "masterRank": 0,
        "specialTrainingStatus": "done",
        "defaultImage": "special_training"
      },
      "userProfile": {
        "userId": 5336465651625988,
        "word": "",
        "honorId1": 127,
        "honorLevel1": 1,
        "honorId2": 105,
        "honorLevel2": 1,
        "honorId3": 108,
        "honorLevel3": 1,
        "twitterId": "",
        "profileImageType": "leader",
        "userVirtualLiveTop10Rankings": []
      }
    }
  ],
  "rank500": [
    {
      "userId": 5135874644520972,
      "score": 2299121,
      "rank": 500,
      "isOwn": false,
      "name": "morua",
      "userCard": {
        "cardId": 111,
        "level": 60,
        "masterRank": 5,
        "specialTrainingStatus": "done",
        "defaultImage": "special_training"
      },
      "userProfile": {
        "userId": 5135874644520972,
        "word": "",
        "honorId1": 129,
        "honorLevel1": 1,
        "twitterId": "",
        "profileImageType": "leader",
        "userVirtualLiveTop10Rankings": []
      }
    }
  ],
  "rank1000": [
    {
      "userId": 5140916285972486,
      "score": 1595893,
      "rank": 1000,
      "isOwn": false,
      "name": "ナチス*曼珠沙華",
      "userCard": {
        "cardId": 4,
        "level": 60,
        "masterRank": 0,
        "specialTrainingStatus": "done",
        "defaultImage": "special_training"
      },
      "userProfile": {
        "userId": 5140916285972486,
        "word": "消失Ｍasterクリアしたいー",
        "honorId1": 33,
        "honorLevel1": 1,
        "honorId2": 37,
        "honorLevel2": 1,
        "honorId3": 123,
        "honorLevel3": 1,
        "twitterId": "",
        "profileImageType": "leader",
        "userVirtualLiveTop10Rankings": []
      }
    }
  ],
  "rank2000": [
    {
      "userId": 5137776673226766,
      "score": 1048411,
      "rank": 2000,
      "isOwn": false,
      "name": "とあるなっちゃん",
      "userCard": {
        "cardId": 111,
        "level": 60,
        "masterRank": 0,
        "specialTrainingStatus": "done",
        "defaultImage": "special_training"
      },
      "userProfile": {
        "userId": 5137776673226766,
        "word": "masterフルコン頑張ってます",
        "honorId1": 13,
        "honorLevel1": 2,
        "honorId2": 146,
        "honorLevel2": 1,
        "honorId3": 107,
        "honorLevel3": 1,
        "twitterId": "",
        "profileImageType": "leader",
        "userVirtualLiveTop10Rankings": []
      }
    }
  ],
  "rank3000": [
    {
      "userId": 5469092094357510,
      "score": 824242,
      "rank": 3000,
      "isOwn": false,
      "name": "いかちゃん",
      "userCard": {
        "cardId": 92,
        "level": 60,
        "masterRank": 0,
        "specialTrainingStatus": "done",
        "defaultImage": "special_training"
      },
      "userProfile": {
        "userId": 5469092094357510,
        "word": "",
        "twitterId": "",
        "profileImageType": "leader",
        "userVirtualLiveTop10Rankings": []
      }
    }
  ],
  "rank4000": [
    {
      "userId": 5193968439058440,
      "score": 703965,
      "rank": 4000,
      "isOwn": false,
      "name": "あきぴ",
      "userCard": {
        "cardId": 88,
        "level": 60,
        "masterRank": 0,
        "specialTrainingStatus": "done",
        "defaultImage": "special_training"
      },
      "userProfile": {
        "userId": 5193968439058440,
        "word": "プロセカやってたらバンドリできなくなってたよね",
        "honorId1": 107,
        "honorLevel1": 1,
        "honorId2": 105,
        "honorLevel2": 1,
        "honorId3": 81,
        "honorLevel3": 1,
        "twitterId": "",
        "profileImageType": "leader",
        "userVirtualLiveTop10Rankings": []
      }
    }
  ],
  "rank5000": [
    {
      "userId": 5513174133202955,
      "score": 618666,
      "rank": 5000,
      "isOwn": false,
      "name": "米欣",
      "userCard": {
        "cardId": 109,
        "level": 60,
        "masterRank": 0,
        "specialTrainingStatus": "done",
        "defaultImage": "special_training"
      },
      "userProfile": {
        "userId": 5513174133202955,
        "word": "",
        "honorId1": 89,
        "honorLevel1": 1,
        "honorId2": 37,
        "honorLevel2": 1,
        "honorId3": 77,
        "honorLevel3": 1,
        "twitterId": "",
        "profileImageType": "leader",
        "userVirtualLiveTop10Rankings": []
      }
    }
  ],
  "rank10000": [
    {
      "userId": 5147740997120010,
      "score": 422013,
      "rank": 10000,
      "isOwn": false,
      "name": "KM*",
      "userCard": {
        "cardId": 88,
        "level": 60,
        "masterRank": 4,
        "specialTrainingStatus": "done",
        "defaultImage": "special_training"
      },
      "userProfile": {
        "userId": 5147740997120010,
        "word": "初音ミクを極めたい、ガルパ民",
        "honorId1": 81,
        "honorLevel1": 2,
        "honorId2": 226,
        "honorLevel2": 1,
        "honorId3": 206,
        "honorLevel3": 1,
        "twitterId": "",
        "profileImageType": "leader",
        "userVirtualLiveTop10Rankings": []
      }
    }
  ],
  "rank20000": [
    {
      "userId": 5198563260792839,
      "score": 301788,
      "rank": 20000,
      "isOwn": false,
      "name": "ふじ",
      "userCard": {
        "cardId": 9,
        "level": 20,
        "masterRank": 5,
        "specialTrainingStatus": "not_doing",
        "defaultImage": "original"
      },
      "userProfile": {
        "userId": 5198563260792839,
        "word": "",
        "honorId1": 33,
        "honorLevel1": 1,
        "honorId2": 37,
        "honorLevel2": 1,
        "honorId3": 77,
        "honorLevel3": 1,
        "twitterId": "",
        "profileImageType": "leader",
        "userVirtualLiveTop10Rankings": []
      }
    }
  ],
  "rank30000": [
    {
      "userId": 5139258906660868,
      "score": 253281,
      "rank": 30000,
      "isOwn": false,
      "name": "ルカ",
      "userCard": {
        "cardId": 96,
        "level": 60,
        "masterRank": 0,
        "specialTrainingStatus": "done",
        "defaultImage": "special_training"
      },
      "userProfile": {
        "userId": 5139258906660868,
        "word": "",
        "honorId1": 89,
        "honorLevel1": 1,
        "honorId2": 105,
        "honorLevel2": 1,
        "honorId3": 77,
        "honorLevel3": 1,
        "twitterId": "",
        "profileImageType": "leader",
        "userVirtualLiveTop10Rankings": []
      }
    }
  ],
  "rank40000": [
    {
      "userId": 5246172705517568,
      "score": 223396,
      "rank": 40000,
      "isOwn": false,
      "name": "ぬのよし",
      "userCard": {
        "cardId": 3,
        "level": 40,
        "masterRank": 0,
        "specialTrainingStatus": "not_doing",
        "defaultImage": "original"
      },
      "userProfile": {
        "userId": 5246172705517568,
        "word": "",
        "honorId1": 81,
        "honorLevel1": 1,
        "honorId2": 105,
        "honorLevel2": 1,
        "honorId3": 129,
        "honorLevel3": 1,
        "twitterId": "",
        "profileImageType": "leader",
        "userVirtualLiveTop10Rankings": []
      }
    }
  ],
  "rank50000": [
    {
      "userId": 5190585258852355,
      "score": 201812,
      "rank": 50000,
      "isOwn": false,
      "name": "ゆめ",
      "userCard": {
        "cardId": 99,
        "level": 41,
        "masterRank": 0,
        "specialTrainingStatus": "done",
        "defaultImage": "special_training"
      },
      "userProfile": {
        "userId": 5190585258852355,
        "word": "",
        "twitterId": "",
        "profileImageType": "leader",
        "userVirtualLiveTop10Rankings": []
      }
    }
  ],
  "rank100000": [
    {
      "userId": 5136949598240770,
      "score": 139949,
      "rank": 100000,
      "isOwn": false,
      "name": "通知来るとキツい笑",
      "userCard": {
        "cardId": 3,
        "level": 23,
        "masterRank": 0,
        "specialTrainingStatus": "not_doing",
        "defaultImage": "original"
      },
      "userProfile": {
        "userId": 5136949598240770,
        "word": "",
        "honorId1": 136,
        "honorLevel1": 1,
        "honorId2": 81,
        "honorLevel2": 1,
        "honorId3": 65,
        "honorLevel3": 1,
        "twitterId": "",
        "profileImageType": "leader",
        "userVirtualLiveTop10Rankings": []
      }
    }
  ]
}